README.md
setup.py
m_monitor.egg-info/PKG-INFO
m_monitor.egg-info/SOURCES.txt
m_monitor.egg-info/dependency_links.txt
m_monitor.egg-info/requires.txt
m_monitor.egg-info/top_level.txt
mobio/libs/monitor/__init__.py