Metadata-Version: 1.0
Name: m-monitor
Version: 0.3
Summary: Monitor các function
Home-page: https://github.com/mobiovn
Author: MOBIO
Author-email: contact@mobio.vn
License: MIT
Platform: UNKNOWN
